micropede/__init__.py
micropede/api.py
micropede/async.py
micropede/client.py
micropede-0.0.27.dist-info/WHEEL
micropede-0.0.27.dist-info/METADATA
micropede-0.0.27.dist-info/RECORD
