Metadata-Version: 1.2
Name: micropede
Version: 0.0.27
Summary: Python interface for Micropede 
Home-page: http://sci-bots.com
License: BSD-2-Clause
Author: Sci-Bots
Author-email: info@sci-bots.com
Requires-Python: >=3.6
Requires-Dist: paho-mqtt
Requires-Dist: wheezy.routing
Requires-Dist: onoff
